grpc_init/__init__.py
grpc_init/__version__.py
grpc_init/cli.py
grpc_init/utils/__init__.py
grpc_init/utils/operations.py
grpc_init-1.0.2.dist-info/licenses/LICENCE
grpc_init-1.0.2.dist-info/METADATA
grpc_init-1.0.2.dist-info/WHEEL
grpc_init-1.0.2.dist-info/entry_points.txt
grpc_init-1.0.2.dist-info/top_level.txt
grpc_init-1.0.2.dist-info/RECORD
