Metadata-Version: 2.4
Name: grpc-init
Version: 1.0.2
Summary: CLI tool to scaffold gRPC service definitions and Python stubs
Author-email: Achraf Mataich <achraf.mataich@outlook.com>
License-Expression: MIT
Classifier: Programming Language :: Python :: 3
Classifier: Operating System :: OS Independent
License-File: LICENCE
Requires-Dist: typer[all]
Requires-Dist: jinja2
Requires-Dist: grpcio-tools
Dynamic: license-file
